componente/data_mem.sv
module data_mem (
    input  logic        clk,
    input  logic        we,          // Write Enable (vem da Unidade de Controle)
    input  logic [31:0] addr,        // Endereço (vem do resultado da ULA)
    input  logic [31:0] wd,          // Write Data (vem do registrador RT)
    output logic [31:0] rd           // Read Data (vai para o registrador de destino)
);

    // Memória de 64 palavras de 32 bits (Pode ser aumentada conforme necessário)
    logic [31:0] ram [0:63];

    // Escrita Síncrona: ocorre na borda de subida do clock
    always_ff @(posedge clk) begin
        if (we) begin
            // Alinhamento: dividimos o endereço por 4 (addr[31:2])
            // para acessar o índice correto do array
            ram[addr[31:2]] <= wd;
        end
    end

    // Leitura Combinacional: o dado fica disponível assim que o endereço chega
    assign rd = ram[addr[31:2]];

endmodule

componente/alu.sv
module alu (
    input  logic [31:0] a,           // Operando A (geralmente RS)
    input  logic [31:0] b,           // Operando B (geralmente RT ou Imediato)
    input  logic [2:0]  alu_control, // Seletor de operação
    output logic [31:0] result,      // Resultado da operação
    output logic        zero         // Flag que indica se o resultado é zero
);

    always_comb begin
        case (alu_control)
            3'b000: result = a & b;          // AND
            3'b001: result = a | b;          // OR
            3'b010: result = a + b;          // ADD (Soma)
            3'b110: result = a - b;          // SUB (Subtração)
            3'b111: result = (a < b) ? 1 : 0; // SLT (Set on Less Than)
            default: result = 32'b0;
        endcase
    end

    // A flag zero é fundamental para instruções de desvio (branch) como o BEQ
    assign zero = (result == 32'b0);

endmodule

componente/sign_extend.sv
module sign_extend (
    input  logic [15:0] a, // Entrada de 16 bits (imediato da instrução)
    output logic [31:0] y  // Saída de 32 bits sinalizada
);

    // O operador de concatenação {32{bit}} repete o bit de sinal 16 vezes
    assign y = {{16{a[15]}}, a};

endmodule

componente/register_file.sv
module register_file (
    input  logic        clk,
    input  logic        we,          // Write Enable (vem da Unidade de Controle)
    input  logic [4:0]  ra1,         // Endereço de leitura 1 (rs)
    input  logic [4:0]  ra2,         // Endereço de leitura 2 (rt)
    input  logic [4:0]  wa,          // Endereço de escrita (rd ou rt)
    input  logic [31:0] wd,          // Dados a serem escritos (vêm da ULA ou Memória)
    output logic [31:0] rd1,         // Saída de dados 1
    output logic [31:0] rd2          // Saída de dados 2
);

    // Array de 32 registradores de 32 bits cada
    logic [31:0] registers [0:31];

    // Lógica de Escrita (Síncrona)
    always_ff @(posedge clk) begin
        if (we && wa != 5'd0) begin
            registers[wa] <= wd;
        end
    end

    // Lógica de Leitura (Combinacional)
    // No MIPS, o registrador 0 ($zero) é sempre 0.
    assign rd1 = (ra1 == 5'd0) ? 32'd0 : registers[ra1];
    assign rd2 = (ra2 == 5'd0) ? 32'd0 : registers[ra2];

endmodule

componente/control_unit.sv
module control_unit (
    input  logic [5:0] opcode,      // instr[31:26]
    input  logic [5:0] funct,       // instr[5:0] (usado para Tipo-R)
    output logic       mem_to_reg,  // Seleciona se o dado p/ o reg vem da ULA ou Memória
    output logic       mem_write,   // Habilita escrita na memória de dados (sw)
    output logic       branch,      // Indica uma instrução de desvio (beq)
    output logic       alu_src,     // Seleciona se o 2º operando da ULA é Reg ou Imediato
    output logic       reg_dst,     // Seleciona se o destino é o campo 'rt' ou 'rd'
    output logic       reg_write,   // Habilita a escrita no Banco de Registradores
    output logic       jump,        // Indica uma instrução de salto (j)
    output logic [2:0] alu_control  // Comando para a ULA
);

    logic [1:0] alu_op;

    // --- Main Decoder ---
    always_comb begin
        // Valores padrão (Reset)
        reg_write  = 0; reg_dst = 0; alu_src = 0; branch = 0;
        mem_write  = 0; mem_to_reg = 0; jump = 0; alu_op = 2'b00;

        case (opcode)
            6'b000000: begin // TIPO-R (add, sub, and, or, slt)
                reg_write = 1; reg_dst = 1; alu_op = 2'b10;
            end
            6'b100011: begin // LW (Load Word)
                reg_write = 1; alu_src = 1; mem_to_reg = 1; alu_op = 2'b00;
            end
            6'b101011: begin // SW (Store Word)
                alu_src = 1; mem_write = 1; alu_op = 2'b00;
            end
            6'b000100: begin // BEQ (Branch if Equal)
                branch = 1; alu_op = 2'b01;
            end
            6'b001000: begin // ADDI (Add Immediate)
                reg_write = 1; alu_src = 1; alu_op = 2'b00;
            end
            6'b000010: begin // J (Jump)
                jump = 1;
            end
            default: ; // Opcode desconhecido
        endcase
    end

    // --- ALU Decoder ---
    // Refina o sinal alu_op usando o campo 'funct' para instruções Tipo-R
    always_comb begin
        case (alu_op)
            2'b00: alu_control = 3'b010; // Soma (usado para lw, sw, addi)
            2'b01: alu_control = 3'b110; // Subtração (usado para beq)
            default: case (funct)        // Tipo-R
                6'b100000: alu_control = 3'b010; // add
                6'b100010: alu_control = 3'b110; // sub
                6'b100100: alu_control = 3'b000; // and
                6'b100101: alu_control = 3'b001; // or
                6'b101010: alu_control = 3'b111; // slt
                default:   alu_control = 3'b000;
            endcase
        endcase
    end

endmodule

componente/instruction_mem.sv
module instruction_mem (
    input  logic [31:0] addr,   // Endereço vindo do PC
    output logic [31:0] instr   // Instrução de 32 bits (MIPS)
);

    // Memória de 256 palavras (1KB de memória de instrução)
    // Você pode aumentar conforme o tamanho do seu programa
    logic [31:0] rom [0:255];

    // Inicialização da memória com o programa em Assembly (binário ou hex)
    initial begin
        // O arquivo deve conter o código de máquina do MIPS
        $readmemh("programa_mips.mem", rom);
    end

    // Lógica de Endereçamento MIPS:
    // Como cada instrução tem 4 bytes, o PC pula de 4 em 4.
    // Para acessar o índice do array [0, 1, 2...], dividimos por 4
    // Isso é feito ignorando os dois bits menos significativos (addr / 4)
    assign instr = rom[addr[31:2]];

endmodule

pc.sv
module pc (
    input  logic        clk,    // Clock do sistema
    input  logic        rst_n,  // Reset assíncrono (ativo em nível baixo)
    input  logic [31:0] pc_in,  // Endereço calculado pela lógica de próxima instrução
    output logic [31:0] pc_out  // Endereço atual enviado para a memória de instruções
);

    always_ff @(posedge clk or negedge rst_n) begin
        if (!rst_n) begin
            
            pc_out <= 32'h0000_0000;
        end else begin

            // No ciclo único, o PC recebe um novo valor a cada ciclo de clock
            pc_out <= pc_in;
        end
    end

endmodule

componente/mips_top.sv
module mips_top (
    input  logic        clk,
    input  logic        rst_n,
    output logic [31:0] pc_out,
    output logic [31:0] alu_result,
    output logic        mem_write
);

    // Sinais internos (pc_out e alu_result e mem_write agora são portas)
    logic [31:0] pc_in, pc_plus_4, pc_branch;
    logic [31:0] instr;
    logic [31:0] rd1, rd2, wd_rf;
    logic [31:0] sign_imm, sign_imm_shl2;
    logic [31:0] alu_src_b;
    logic [31:0] read_data;
    logic [4:0]  write_reg;
    logic        zero;

    // Sinais de controle
    logic reg_write, reg_dst, alu_src, branch, mem_to_reg, jump;
    logic [2:0] alu_control;

    // --- 1. Busca da Instrução (Fetch) ---
    pc p_counter (
        .clk(clk),
        .rst_n(rst_n),
        .pc_in(pc_in),
        .pc_out(pc_out)
    );

    instruction_mem i_mem (
        .addr(pc_out),
        .instr(instr)
    );

    // Somador PC + 4
    assign pc_plus_4 = pc_out + 4;

    // --- 2. Decodificação e Banco de Registradores ---
    control_unit c_unit (
        .opcode(instr[31:26]),
        .funct(instr[5:0]),
        .mem_to_reg(mem_to_reg),
        .mem_write(mem_write),
        .branch(branch),
        .alu_src(alu_src),
        .reg_dst(reg_dst),
        .reg_write(reg_write),
        .jump(jump),
        .alu_control(alu_control)
    );

    // Mux para decidir o registrador de destino (Tipo-R usa RD, Tipo-I usa RT)
    assign write_reg = reg_dst ? instr[15:11] : instr[20:16];

    register_file reg_file (
        .clk(clk),
        .we(reg_write),
        .ra1(instr[25:21]),
        .ra2(instr[20:16]),
        .wa(write_reg),
        .wd(wd_rf),
        .rd1(rd1),
        .rd2(rd2)
    );

    sign_extend s_ext (
        .a(instr[15:0]),
        .y(sign_imm)
    );

    // --- 3. Execução (ULA) ---
    // Mux para a entrada B da ULA (Registrador ou Imediato)
    assign alu_src_b = alu_src ? sign_imm : rd2;

    alu main_alu (
        .a(rd1),
        .b(alu_src_b),
        .alu_control(alu_control),
        .result(alu_result),
        .zero(zero)
    );

    // --- 4. Memória de Dados e Escrita (Write Back) ---
    data_mem d_mem (
        .clk(clk),
        .we(mem_write),
        .addr(alu_result),
        .wd(rd2),
        .rd(read_data)
    );

    // Mux final: O que volta para o registrador? (Dado da RAM ou resultado da ULA)
    assign wd_rf = mem_to_reg ? read_data : alu_result;

    // --- 5. Lógica de Próximo PC (Branch e Jump) ---
    // Cálculo do endereço de Branch
    assign sign_imm_shl2 = {sign_imm[29:0], 2'b00};
    assign pc_branch = pc_plus_4 + sign_imm_shl2;

    // Mux para decidir entre PC+4 ou Branch
    logic [31:0] pc_next_branch;
    assign pc_next_branch = (branch & zero) ? pc_branch : pc_plus_4;

    // Mux para decidir entre o anterior ou Jump direto
    // Endereço de Jump: (PC+4)[31:28] concatenado com instr[25:0] << 2
    logic [31:0] pc_jump;
    assign pc_jump = {pc_plus_4[31:28], instr[25:0], 2'b00};

    assign pc_in = jump ? pc_jump : pc_next_branch;

endmodule

testbench/mips_top_tb.sv
`timescale 1ns / 1ps

// =============================================================================
//  Testbench Completo: mips_top_tb
//  Processador MIPS Monociclo
//
//  Cobertura de testes:
//    [1] Reset do processador (PC deve partir do 0)
//    [2] ADDI $s0, $zero, 5    -> $s0 = 5
//    [3] ADDI $s1, $zero, 10   -> $s1 = 10
//    [4] ADD  $s2, $s0, $s1    -> $s2 = 15
//    [5] Verificação de sequência de PC (0x00 -> 0x04 -> 0x08 -> 0x0C)
//    [6] Instrução NOP/inválida não deve alterar estado
//    [7] mem_write deve ficar inativo (sem SW no programa)
//    [8] Relatório final de PASS/FAIL
// =============================================================================

module mips_top_tb;

    // -------------------------------------------------------------------------
    //  Sinais do DUT
    // -------------------------------------------------------------------------
    logic        clk;
    logic        rst_n;
    logic [31:0] pc_out;
    logic [31:0] alu_result;
    logic        mem_write;

    // -------------------------------------------------------------------------
    //  Contadores de erros e testes
    // -------------------------------------------------------------------------
    int unsigned test_count = 0;
    int unsigned fail_count = 0;

    // -------------------------------------------------------------------------
    //  Instanciação do DUT
    // -------------------------------------------------------------------------
    mips_top dut (
        .clk       (clk),
        .rst_n     (rst_n),
        .pc_out    (pc_out),
        .alu_result(alu_result),
        .mem_write (mem_write)
    );

    // -------------------------------------------------------------------------
    //  Clock: período de 20 ns (50 MHz)
    // -------------------------------------------------------------------------
    initial clk = 0;
    always #10 clk = ~clk;

    // -------------------------------------------------------------------------
    //  Tarefa auxiliar: verifica uma condição e reporta PASS/FAIL
    // -------------------------------------------------------------------------
    task automatic check(
        input string  test_name,
        input logic   condition
    );
        test_count++;
        if (condition) begin
            $display("  [PASS] %s", test_name);
        end else begin
            $display("  [FAIL] %s", test_name);
            fail_count++;
        end
    endtask

    // -------------------------------------------------------------------------
    //  Tarefa: aguarda N ciclos de clock (borda de subida)
    // -------------------------------------------------------------------------
    task automatic wait_cycles(input int unsigned n);
        repeat (n) @(posedge clk);
        #1; // pequeno atraso após a borda para amostrar saídas estabilizadas
    endtask

    // -------------------------------------------------------------------------
    //  Bloco de estímulo principal
    // -------------------------------------------------------------------------
    initial begin
        // --- Waveform dump ---
        $dumpfile("mips_top_tb.vcd");
        $dumpvars(0, mips_top_tb);

        $display("=============================================================");
        $display("  Testbench Completo - Processador MIPS Monociclo");
        $display("=============================================================");

        // =====================================================================
        //  TESTE 1: Reset
        // =====================================================================
        $display("\n--- BLOCO 1: Reset do Processador ---");

        clk   = 0;
        rst_n = 0;  // Ativa reset (ativo baixo)

        // Aguarda 2 ciclos em reset
        wait_cycles(2);

        check("PC == 0x00000000 durante reset",   pc_out === 32'h0000_0000);
        check("mem_write == 0 durante reset",      mem_write === 1'b0);

        // =====================================================================
        //  TESTE 2: Ciclo 1 — ADDI $s0, $zero, 5
        //    Instrução: 0x20100005
        //    $s0 (reg 16) deve receber 5 após a borda de escrita
        // =====================================================================
        $display("\n--- BLOCO 2: ADDI $s0, $zero, 5 ---");

        rst_n = 1;              // Libera reset
        wait_cycles(1);         // Executa ciclo da instrução em PC=0x00

        check("PC == 0x00000004 (apos ADDI $s0)",
              pc_out === 32'h0000_0004);
        check("ALU result == 5 (imediato para $s0)",
              alu_result === 32'd5);
        check("$s0 == 5",
              dut.reg_file.registers[16] === 32'd5);
        check("mem_write == 0 (ADDI nao escreve na mem)",
              mem_write === 1'b0);

        // =====================================================================
        //  TESTE 3: Ciclo 2 — ADDI $s1, $zero, 10
        //    Instrução: 0x2011000A
        //    $s1 (reg 17) deve receber 10
        // =====================================================================
        $display("\n--- BLOCO 3: ADDI $s1, $zero, 10 ---");

        wait_cycles(1);         // Executa ciclo da instrução em PC=0x04

        check("PC == 0x00000008 (apos ADDI $s1)",
              pc_out === 32'h0000_0008);
        check("ALU result == 10 (imediato para $s1)",
              alu_result === 32'd10);
        check("$s1 == 10",
              dut.reg_file.registers[17] === 32'd10);
        check("$s0 ainda == 5 (sem regressao)",
              dut.reg_file.registers[16] === 32'd5);

        // =====================================================================
        //  TESTE 4: Ciclo 3 — ADD $s2, $s0, $s1
        //    Instrução: 0x02119020
        //    $s2 (reg 18) deve receber 5 + 10 = 15
        // =====================================================================
        $display("\n--- BLOCO 4: ADD $s2, $s0, $s1 ---");

        wait_cycles(1);         // Executa ciclo da instrução em PC=0x08

        check("PC == 0x0000000C (apos ADD $s2)",
              pc_out === 32'h0000_000C);
        check("ALU result == 15 (5 + 10)",
              alu_result === 32'd15);
        check("$s2 == 15",
              dut.reg_file.registers[18] === 32'd15);
        check("$s0 nao foi alterado pelo ADD",
              dut.reg_file.registers[16] === 32'd5);
        check("$s1 nao foi alterado pelo ADD",
              dut.reg_file.registers[17] === 32'd10);

        // =====================================================================
        //  TESTE 5: mem_write deve ter permanecido 0 ao longo de todo o programa
        //    (não há instrução SW no programa)
        // =====================================================================
        $display("\n--- BLOCO 5: Sinal mem_write ---");

        check("mem_write == 0 apos execucao do programa (sem SW)",
              mem_write === 1'b0);

        // =====================================================================
        //  TESTE 6: Novo reset — PC deve voltar para 0
        // =====================================================================
        $display("\n--- BLOCO 6: Novo Reset ---");

        rst_n = 0;
        wait_cycles(1);

        check("PC retorna a 0x00000000 apos segundo reset",
              pc_out === 32'h0000_0000);

        rst_n = 1;

        // =====================================================================
        //  Relatório final
        // =====================================================================
        $display("\n=============================================================");
        $display("  RESULTADO FINAL: %0d/%0d testes passaram.",
                 test_count - fail_count, test_count);
        if (fail_count == 0)
            $display("  *** TODOS OS TESTES PASSARAM COM SUCESSO! ***");
        else
            $display("  *** ATENCAO: %0d TESTE(S) FALHARAM! ***", fail_count);
        $display("=============================================================\n");

        $finish;
    end

    // -------------------------------------------------------------------------
    //  Monitor contínuo (visível no terminal durante a simulação)
    // -------------------------------------------------------------------------
    initial begin
        $display("\n  Tempo(ns) | PC       | Instr    | ALU_Res  | $s0 | $s1 | $s2 | MW");
        $display("  ----------+----------+----------+----------+-----+-----+-----+---");
        forever begin
            @(posedge clk);
            #1;
            $display("  %8t  | %h | %h | %h | %3d | %3d | %3d | %b",
                $time,
                pc_out,
                dut.instr,
                alu_result,
                dut.reg_file.registers[16],
                dut.reg_file.registers[17],
                dut.reg_file.registers[18],
                mem_write);
        end
    end

    // -------------------------------------------------------------------------
    //  Timeout de segurança: aborta simulação se travar
    // -------------------------------------------------------------------------
    initial begin
        #10_000;
        $display("\n[TIMEOUT] Simulacao excedeu 10us — possivel loop infinito!");
        $finish;
    end

endmodule

Arquivos_.vcd/mips_top_tb.vcd
$date
	Sat May  2 22:44:49 2026
$end
$version
	Icarus Verilog
$end
$timescale
	1ps
$end
$scope module mips_top_tb $end
$var reg 1 ! clk $end
$var reg 1 " rst_n $end
$scope module dut $end
$var wire 1 ! clk $end
$var wire 1 " rst_n $end
$var wire 1 # zero $end
$var wire 5 $ write_reg [4:0] $end
$var wire 32 % wd_rf [31:0] $end
$var wire 32 & sign_imm_shl2 [31:0] $end
$var wire 32 ' sign_imm [31:0] $end
$var wire 1 ( reg_write $end
$var wire 1 ) reg_dst $end
$var wire 32 * read_data [31:0] $end
$var wire 32 + rd2 [31:0] $end
$var wire 32 , rd1 [31:0] $end
$var wire 32 - pc_plus_4 [31:0] $end
$var wire 32 . pc_out [31:0] $end
$var wire 32 / pc_next_branch [31:0] $end
$var wire 32 0 pc_jump [31:0] $end
$var wire 32 1 pc_in [31:0] $end
$var wire 32 2 pc_branch [31:0] $end
$var wire 1 3 mem_write $end
$var wire 1 4 mem_to_reg $end
$var wire 1 5 jump $end
$var wire 32 6 instr [31:0] $end
$var wire 1 7 branch $end
$var wire 32 8 alu_src_b [31:0] $end
$var wire 1 9 alu_src $end
$var wire 32 : alu_result [31:0] $end
$var wire 3 ; alu_control [2:0] $end
$scope module c_unit $end
$var wire 6 < funct [5:0] $end
$var wire 6 = opcode [5:0] $end
$var reg 3 > alu_control [2:0] $end
$var reg 2 ? alu_op [1:0] $end
$var reg 1 9 alu_src $end
$var reg 1 7 branch $end
$var reg 1 5 jump $end
$var reg 1 4 mem_to_reg $end
$var reg 1 3 mem_write $end
$var reg 1 ) reg_dst $end
$var reg 1 ( reg_write $end
$upscope $end
$scope module d_mem $end
$var wire 1 ! clk $end
$var wire 32 @ rd [31:0] $end
$var wire 1 3 we $end
$var wire 32 A wd [31:0] $end
$var wire 32 B addr [31:0] $end
$upscope $end
$scope module i_mem $end
$var wire 32 C instr [31:0] $end
$var wire 32 D addr [31:0] $end
$upscope $end
$scope module main_alu $end
$var wire 3 E alu_control [2:0] $end
$var wire 32 F b [31:0] $end
$var wire 1 # zero $end
$var wire 32 G a [31:0] $end
$var reg 32 H result [31:0] $end
$upscope $end
$scope module p_counter $end
$var wire 1 ! clk $end
$var wire 32 I pc_in [31:0] $end
$var wire 1 " rst_n $end
$var reg 32 J pc_out [31:0] $end
$upscope $end
$scope module reg_file $end
$var wire 1 ! clk $end
$var wire 5 K ra1 [4:0] $end
$var wire 5 L ra2 [4:0] $end
$var wire 5 M wa [4:0] $end
$var wire 32 N wd [31:0] $end
$var wire 1 ( we $end
$var wire 32 O rd2 [31:0] $end
$var wire 32 P rd1 [31:0] $end
$upscope $end
$scope module s_ext $end
$var wire 16 Q a [15:0] $end
$var wire 32 R y [31:0] $end
$upscope $end
$upscope $end
$upscope $end
$scope module mips_top_tb $end
$scope module dut $end
$scope module c_unit $end
$upscope $end
$scope module d_mem $end
$upscope $end
$scope module i_mem $end
$upscope $end
$scope module main_alu $end
$upscope $end
$scope module p_counter $end
$upscope $end
$scope module reg_file $end
$upscope $end
$scope module s_ext $end
$upscope $end
$upscope $end
$upscope $end
$enddefinitions $end
$comment Show the parameter values. $end
$dumpall
$end
#0
$dumpvars
b101 R
b101 Q
b0 P
bx O
b101 N
b10000 M
b10000 L
b0 K
b0 J
b100 I
b101 H
b0 G
b101 F
b10 E
b0 D
b100000000100000000000000000101 C
b101 B
bx A
bx @
b0 ?
b10 >
b1000 =
b101 <
b10 ;
b101 :
19
b101 8
07
b100000000100000000000000000101 6
05
04
03
b11000 2
b100 1
b10000000000000000010100 0
b100 /
b0 .
b100 -
b0 ,
bx +
bx *
0)
1(
b101 '
b10100 &
b101 %
b10000 $
0#
0"
0!
$end
#5000
b101 +
b101 A
b101 O
1!
#10000
0!
#15000
1!
#20000
0!
1"
#25000
b1010 %
b1010 N
b101000 &
b1010 :
b1010 B
b1010 H
b1010 8
b1010 F
bx +
bx A
bx O
b10001000000000000101000 0
b1010 '
b1010 R
b10001 $
b10001 M
b1010 Q
b10001 L
b1010 <
b1000 1
b1000 I
b100000000100010000000000001010 6
b100000000100010000000000001010 C
b1000 /
b110000 2
b1000 -
b100 .
b100 D
b100 J
1!
#30000
0!
#35000
b11111111111111100100000010000000 &
b1111 %
b1111 N
b1111 :
b1111 B
b1111 H
b10010 $
b10010 M
b1000010001100100000010000000 0
b11111111111111111001000000100000 '
b11111111111111111001000000100000 R
b101 ,
b101 G
b101 P
b10 ?
1)
09
1(
b1001000000100000 Q
b10000 K
b100000 <
b0 =
b1100 1
b1100 I
b1010 +
b1010 A
b1010 O
b10000100011001000000100000 6
b10000100011001000000100000 C
b1100 /
b11111111111111100100000010001100 2
b1100 -
b1000 .
b1000 D
b1000 J
1!
#40000
0!
#45000
bx00 &
bx %
bx N
bx 8
bx F
x#
bx :
bx B
bx H
b0xxxxxxxxxxxxxxxxxxxxxxxxxx00 0
bx '
bx R
bx +
bx A
bx O
bx ,
bx G
bx P
bx $
bx M
b0 ?
0)
0(
bx Q
bx L
bx K
bx <
bx =
b10000 1
b10000 I
bx 6
bx C
b10000 /
bx 2
b10000 -
b1100 .
b1100 D
b1100 J
1!
#50000
0!
#55000
b10100 1
b10100 I
b10100 /
b10100 -
b10000 .
b10000 D
b10000 J
1!
#60000
0!
#65000
b11000 1
b11000 I
b11000 /
b11000 -
b10100 .
b10100 D
b10100 J
1!
#70000
0!
#75000
b11100 1
b11100 I
b11100 /
b11100 -
b11000 .
b11000 D
b11000 J
1!
#80000
0!
#85000
b100000 1
b100000 I
b100000 /
b100000 -
b11100 .
b11100 D
b11100 J
1!
#90000
0!
#95000
b100100 1
b100100 I
b100100 /
b100100 -
b100000 .
b100000 D
b100000 J
1!
#100000
0!
#105000
b101000 1
b101000 I
b101000 /
b101000 -
b100100 .
b100100 D
b100100 J
1!
#110000
0!
#115000
b101100 1
b101100 I
b101100 /
b101100 -
b101000 .
b101000 D
b101000 J
1!
#120000
0!
#125000
b110000 1
b110000 I
b110000 /
b110000 -
b101100 .
b101100 D
b101100 J
1!
#130000
0!
#135000
b110100 1
b110100 I
b110100 /
b110100 -
b110000 .
b110000 D
b110000 J
1!
#140000
0!
#145000
b111000 1
b111000 I
b111000 /
b111000 -
b110100 .
b110100 D
b110100 J
1!
#150000
0!
#155000
b111100 1
b111100 I
b111100 /
b111100 -
b111000 .
b111000 D
b111000 J
1!
#160000
0!
#165000
b1000000 1
b1000000 I
b1000000 /
b1000000 -
b111100 .
b111100 D
b111100 J
1!
#170000
0!
#175000
b1000100 1
b1000100 I
b1000100 /
b1000100 -
b1000000 .
b1000000 D
b1000000 J
1!
#180000
0!
#185000
b1001000 1
b1001000 I
b1001000 /
b1001000 -
b1000100 .
b1000100 D
b1000100 J
1!
#190000
0!
#195000
b1001100 1
b1001100 I
b1001100 /
b1001100 -
b1001000 .
b1001000 D
b1001000 J
1!
#200000
0!
#205000
b1010000 1
b1010000 I
b1010000 /
b1010000 -
b1001100 .
b1001100 D
b1001100 J
1!
#210000
0!
#215000
b1010100 1
b1010100 I
b1010100 /
b1010100 -
b1010000 .
b1010000 D
b1010000 J
1!
#220000
0!
#225000
b1011000 1
b1011000 I
b1011000 /
b1011000 -
b1010100 .
b1010100 D
b1010100 J
1!
#230000
0!
#235000
b1011100 1
b1011100 I
b1011100 /
b1011100 -
b1011000 .
b1011000 D
b1011000 J
1!
#240000
0!
#245000
b1100000 1
b1100000 I
b1100000 /
b1100000 -
b1011100 .
b1011100 D
b1011100 J
1!
#250000
0!
#255000
b1100100 1
b1100100 I
b1100100 /
b1100100 -
b1100000 .
b1100000 D
b1100000 J
1!
#260000
0!
#265000
b1101000 1
b1101000 I
b1101000 /
b1101000 -
b1100100 .
b1100100 D
b1100100 J
1!
#270000
0!
#275000
b1101100 1
b1101100 I
b1101100 /
b1101100 -
b1101000 .
b1101000 D
b1101000 J
1!
#280000
0!
#285000
b1110000 1
b1110000 I
b1110000 /
b1110000 -
b1101100 .
b1101100 D
b1101100 J
1!
#290000
0!
#295000
b1110100 1
b1110100 I
b1110100 /
b1110100 -
b1110000 .
b1110000 D
b1110000 J
1!
#300000
0!
#305000
b1111000 1
b1111000 I
b1111000 /
b1111000 -
b1110100 .
b1110100 D
b1110100 J
1!
#310000
0!
#315000
b1111100 1
b1111100 I
b1111100 /
b1111100 -
b1111000 .
b1111000 D
b1111000 J
1!
#320000
0!
#325000
b10000000 1
b10000000 I
b10000000 /
b10000000 -
b1111100 .
b1111100 D
b1111100 J
1!
#330000
0!
#335000
b10000100 1
b10000100 I
b10000100 /
b10000100 -
b10000000 .
b10000000 D
b10000000 J
1!
#340000
0!
#345000
b10001000 1
b10001000 I
b10001000 /
b10001000 -
b10000100 .
b10000100 D
b10000100 J
1!
#350000
0!
#355000
b10001100 1
b10001100 I
b10001100 /
b10001100 -
b10001000 .
b10001000 D
b10001000 J
1!
#360000
0!
#365000
b10010000 1
b10010000 I
b10010000 /
b10010000 -
b10001100 .
b10001100 D
b10001100 J
1!
#370000
0!
#375000
b10010100 1
b10010100 I
b10010100 /
b10010100 -
b10010000 .
b10010000 D
b10010000 J
1!
#380000
0!
#385000
b10011000 1
b10011000 I
b10011000 /
b10011000 -
b10010100 .
b10010100 D
b10010100 J
1!
#390000
0!
#395000
b10011100 1
b10011100 I
b10011100 /
b10011100 -
b10011000 .
b10011000 D
b10011000 J
1!
#400000
0!
#405000
b10100000 1
b10100000 I
b10100000 /
b10100000 -
b10011100 .
b10011100 D
b10011100 J
1!
#410000
0!
#415000
b10100100 1
b10100100 I
b10100100 /
b10100100 -
b10100000 .
b10100000 D
b10100000 J
1!
#420000
0!
#425000
b10101000 1
b10101000 I
b10101000 /
b10101000 -
b10100100 .
b10100100 D
b10100100 J
1!
#430000
0!
#435000
b10101100 1
b10101100 I
b10101100 /
b10101100 -
b10101000 .
b10101000 D
b10101000 J
1!
#440000
0!
#445000
b10110000 1
b10110000 I
b10110000 /
b10110000 -
b10101100 .
b10101100 D
b10101100 J
1!
#450000
0!
#455000
b10110100 1
b10110100 I
b10110100 /
b10110100 -
b10110000 .
b10110000 D
b10110000 J
1!
#460000
0!
#465000
b10111000 1
b10111000 I
b10111000 /
b10111000 -
b10110100 .
b10110100 D
b10110100 J
1!
#470000
0!
#475000
b10111100 1
b10111100 I
b10111100 /
b10111100 -
b10111000 .
b10111000 D
b10111000 J
1!
#480000
0!
#485000
b11000000 1
b11000000 I
b11000000 /
b11000000 -
b10111100 .
b10111100 D
b10111100 J
1!
#490000
0!
#495000
b11000100 1
b11000100 I
b11000100 /
b11000100 -
b11000000 .
b11000000 D
b11000000 J
1!
#500000
0!
#505000
b11001000 1
b11001000 I
b11001000 /
b11001000 -
b11000100 .
b11000100 D
b11000100 J
1!
#510000
0!
#515000
b11001100 1
b11001100 I
b11001100 /
b11001100 -
b11001000 .
b11001000 D
b11001000 J
1!
